[
    { "name": "Barbell Back Squat", "bodyParts": ["Quads", "Glutes"], "equipment": "Barbell" },
    { "name": "Barbell Front Squat", "bodyParts": ["Quads", "Glutes"], "equipment": "Barbell" },
    { "name": "Goblet Squat", "bodyParts": ["Quads", "Glutes"], "equipment": "Dumbbell" },
    { "name": "Bodyweight Squat", "bodyParts": ["Quads", "Glutes"], "equipment": "Bodyweight" },
    { "name": "Box Squat", "bodyParts": ["Quads", "Glutes"], "equipment": "Barbell" },
    { "name": "Hack Squat", "bodyParts": ["Quads", "Glutes"], "equipment": "Machine" },
    { "name": "Leg Press", "bodyParts": ["Quads", "Glutes"], "equipment": "Machine" },
    { "name": "Walking Lunge", "bodyParts": ["Quads", "Glutes"], "equipment": "Dumbbell" },
    { "name": "Reverse Lunge", "bodyParts": ["Quads", "Glutes"], "equipment": "Dumbbell" },
    { "name": "Bulgarian Split Squat", "bodyParts": ["Quads", "Glutes"], "equipment": "Dumbbell" },
    { "name": "Step-Up", "bodyParts": ["Quads", "Glutes"], "equipment": "Dumbbell" },
    { "name": "Sissy Squat", "bodyParts": ["Quads"], "equipment": "Machine" },
    { "name": "Romanian Deadlift", "bodyParts": ["Hamstrings", "Glutes"], "equipment": "Barbell" },
    { "name": "Stiff-Leg Deadlift", "bodyParts": ["Hamstrings", "Glutes"], "equipment": "Barbell" },
    { "name": "Trap Bar Deadlift", "bodyParts": ["Quads", "Glutes"], "equipment": "Trap Bar" },
    { "name": "Good Morning", "bodyParts": ["Hamstrings", "Glutes"], "equipment": "Barbell" },
    { "name": "Hip Thrust", "bodyParts": ["Glutes", "Hamstrings"], "equipment": "Barbell" },
    { "name": "Glute Bridge", "bodyParts": ["Glutes", "Hamstrings"], "equipment": "Barbell" },
    { "name": "Cable Pull-Through", "bodyParts": ["Glutes", "Hamstrings"], "equipment": "Cable" },
    { "name": "Seated Leg Curl", "bodyParts": ["Hamstrings"], "equipment": "Machine" },
    { "name": "Lying Leg Curl", "bodyParts": ["Hamstrings"], "equipment": "Machine" },
    { "name": "Leg Extension", "bodyParts": ["Quads"], "equipment": "Machine" },
    { "name": "Standing Calf Raise", "bodyParts": ["Calves"], "equipment": "Machine" },
    { "name": "Seated Calf Raise", "bodyParts": ["Calves"], "equipment": "Machine" },
    { "name": "Donkey Calf Raise", "bodyParts": ["Calves"], "equipment": "Machine" },
    { "name": "Barbell Bench Press (Flat)", "bodyParts": ["Chest", "Triceps"], "equipment": "Barbell" },
    { "name": "Barbell Bench Press (Incline)", "bodyParts": ["Chest", "Shoulders"], "equipment": "Barbell" },
    { "name": "Barbell Bench Press (Decline)", "bodyParts": ["Chest"], "equipment": "Barbell" },
    { "name": "Dumbbell Bench Press (Flat)", "bodyParts": ["Chest"], "equipment": "Dumbbell" },
    { "name": "Dumbbell Bench Press (Incline)", "bodyParts": ["Chest", "Shoulders"], "equipment": "Dumbbell" },
    { "name": "Dumbbell Bench Press (Decline)", "bodyParts": ["Chest"], "equipment": "Dumbbell" },
    { "name": "Machine Chest Press", "bodyParts": ["Chest"], "equipment": "Machine" },
    { "name": "Push-Up", "bodyParts": ["Chest", "Triceps"], "equipment": "Bodyweight" },
    { "name": "Weighted Push-Up", "bodyParts": ["Chest", "Triceps"], "equipment": "Plate" },
    { "name": "Chest Dip", "bodyParts": ["Chest", "Triceps"], "equipment": "Bodyweight" },
    { "name": "Cable Crossover (High to Low)", "bodyParts": ["Chest"], "equipment": "Cable" },
    { "name": "Cable Crossover (Low to High)", "bodyParts": ["Chest"], "equipment": "Cable" },
    { "name": "Pec Deck Fly", "bodyParts": ["Chest"], "equipment": "Machine" },
    { "name": "Dumbbell Fly (Flat)", "bodyParts": ["Chest"], "equipment": "Dumbbell" },
    { "name": "Dumbbell Fly (Incline)", "bodyParts": ["Chest"], "equipment": "Dumbbell" },
    { "name": "Pull-Up", "bodyParts": ["Back", "Biceps"], "equipment": "Bodyweight" },
    { "name": "Chin-Up", "bodyParts": ["Back", "Biceps"], "equipment": "Bodyweight" },
    { "name": "Lat Pulldown (Wide Grip)", "bodyParts": ["Lats"], "equipment": "Machine" },
    { "name": "Lat Pulldown (Close Grip)", "bodyParts": ["Lats"], "equipment": "Machine" },
    { "name": "Seated Cable Row", "bodyParts": ["Lats", "Rhomboids"], "equipment": "Cable" },
    { "name": "T-Bar Row", "bodyParts": ["Lats", "Rhomboids"], "equipment": "Machine" },
    { "name": "Barbell Row", "bodyParts": ["Lats", "Rear Delts"], "equipment": "Barbell" },
    { "name": "Dumbbell Row (One Arm)", "bodyParts": ["Lats", "Rear Delts"], "equipment": "Dumbbell" },
    { "name": "Chest-Supported Row", "bodyParts": ["Lats"], "equipment": "Machine" },
    { "name": "Meadows Row", "bodyParts": ["Lats"], "equipment": "Barbell" },
    { "name": "Straight-Arm Pulldown", "bodyParts": ["Lats"], "equipment": "Cable" },
    { "name": "Face Pull", "bodyParts": ["Rear Delts", "Traps"], "equipment": "Cable" },
    { "name": "Barbell Overhead Press", "bodyParts": ["Shoulders", "Triceps"], "equipment": "Barbell" },
    { "name": "Seated Barbell Overhead Press", "bodyParts": ["Shoulders"], "equipment": "Barbell" },
    { "name": "Dumbbell Shoulder Press", "bodyParts": ["Shoulders"], "equipment": "Dumbbell" },
    { "name": "Arnold Press", "bodyParts": ["Shoulders"], "equipment": "Dumbbell" },
    { "name": "Machine Shoulder Press", "bodyParts": ["Shoulders"], "equipment": "Machine" },
    { "name": "Lateral Raise", "bodyParts": ["Shoulders"], "equipment": "Dumbbell" },
    { "name": "Cable Lateral Raise", "bodyParts": ["Shoulders"], "equipment": "Cable" },
    { "name": "Machine Lateral Raise", "bodyParts": ["Shoulders"], "equipment": "Machine" },
    { "name": "Front Raise", "bodyParts": ["Front Delts"], "equipment": "Plate" },
    { "name": "Rear Delt Fly (Dumbbell)", "bodyParts": ["Rear Delts"], "equipment": "Dumbbell" },
    { "name": "Reverse Pec Deck", "bodyParts": ["Rear Delts"], "equipment": "Machine" },
    { "name": "Upright Row", "bodyParts": ["Shoulders", "Traps"], "equipment": "Barbell" },
    { "name": "Barbell Curl", "bodyParts": ["Biceps"], "equipment": "Barbell" },
    { "name": "EZ-Bar Curl", "bodyParts": ["Biceps"], "equipment": "EZ Bar" },
    { "name": "Dumbbell Curl", "bodyParts": ["Biceps"], "equipment": "Dumbbell" },
    { "name": "Incline Dumbbell Curl", "bodyParts": ["Biceps"], "equipment": "Dumbbell" },
    { "name": "Hammer Curl", "bodyParts": ["Biceps", "Forearms"], "equipment": "Dumbbell" },
    { "name": "Cable Curl", "bodyParts": ["Biceps"], "equipment": "Cable" },
    { "name": "Preacher Curl", "bodyParts": ["Biceps"], "equipment": "Machine" },
    { "name": "Concentration Curl", "bodyParts": ["Biceps"], "equipment": "Dumbbell" },
    { "name": "Reverse Curl", "bodyParts": ["Forearms"], "equipment": "EZ Bar" },
    { "name": "Wrist Curl", "bodyParts": ["Forearms"], "equipment": "Barbell" },
    { "name": "Skullcrusher (EZ-Bar)", "bodyParts": ["Triceps"], "equipment": "EZ Bar" },
    { "name": "Dumbbell Skullcrusher", "bodyParts": ["Triceps"], "equipment": "Dumbbell" },
    { "name": "Cable Triceps Pushdown (Bar)", "bodyParts": ["Triceps"], "equipment": "Cable" },
    { "name": "Cable Triceps Pushdown (Rope)", "bodyParts": ["Triceps"], "equipment": "Cable" },
    { "name": "Overhead Triceps Extension (Dumbbell)", "bodyParts": ["Triceps"], "equipment": "Dumbbell" },
    { "name": "Overhead Triceps Extension (Cable)", "bodyParts": ["Triceps"], "equipment": "Cable" },
    { "name": "Bench Dip", "bodyParts": ["Triceps", "Chest"], "equipment": "Bodyweight" },
    { "name": "Close-Grip Bench Press", "bodyParts": ["Triceps", "Chest"], "equipment": "Barbell" },
    { "name": "Cable Crunch", "bodyParts": ["Abs"], "equipment": "Cable" },
    { "name": "Hanging Leg Raise", "bodyParts": ["Abs"], "equipment": "Bodyweight" },
    { "name": "Captain’s Chair Leg Raise", "bodyParts": ["Abs"], "equipment": "Machine" },
    { "name": "Decline Sit-Up", "bodyParts": ["Abs"], "equipment": "Bodyweight" },
    { "name": "Plank", "bodyParts": ["Abs", "Core"], "equipment": "Bodyweight" },
    { "name": "Ab Wheel Rollout", "bodyParts": ["Abs", "Core"], "equipment": "Ab Wheel" },
    { "name": "Russian Twist", "bodyParts": ["Obliques"], "equipment": "Dumbbell" },
    { "name": "Side Plank", "bodyParts": ["Obliques"], "equipment": "Bodyweight" },
    { "name": "Pallof Press", "bodyParts": ["Core"], "equipment": "Cable" },
    { "name": "Farmer’s Carry", "bodyParts": ["Full Body"], "equipment": "Dumbbell" },
    { "name": "Sled Push", "bodyParts": ["Quads", "Glutes"], "equipment": "Sled" },
    { "name": "Sled Pull", "bodyParts": ["Back", "Glutes"], "equipment": "Sled" },
    { "name": "Kettlebell Swing", "bodyParts": ["Hamstrings", "Glutes"], "equipment": "Kettlebell" },
    { "name": "Turkish Get-Up", "bodyParts": ["Full Body"], "equipment": "Kettlebell" },
    { "name": "Single-Leg Deadlift", "bodyParts": ["Hamstrings", "Glutes"], "equipment": "Dumbbell" },
    { "name": "Sumo Deadlift", "bodyParts": ["Hamstrings", "Glutes", "Quads"], "equipment": "Barbell" },
    { "name": "Deficit Deadlift", "bodyParts": ["Hamstrings", "Glutes"], "equipment": "Barbell" },
    { "name": "Snatch-Grip Deadlift", "bodyParts": ["Back", "Hamstrings"], "equipment": "Barbell" },
    { "name": "Conventional Deadlift", "bodyParts": ["Back", "Hamstrings", "Glutes"], "equipment": "Barbell" },
    { "name": "Rack Pull", "bodyParts": ["Back", "Traps"], "equipment": "Barbell" },
    { "name": "Hip Abduction", "bodyParts": ["Glutes"], "equipment": "Machine" },
    { "name": "Hip Adduction", "bodyParts": ["Adductors"], "equipment": "Machine" },
    { "name": "Cable Kickback", "bodyParts": ["Glutes"], "equipment": "Cable" },
    { "name": "Standing Glute Kickback", "bodyParts": ["Glutes"], "equipment": "Cable" },
    { "name": "Glute Kickback (Machine)", "bodyParts": ["Glutes"], "equipment": "Machine" },
    { "name": "Landmine Squat Press", "bodyParts": ["Quads", "Glutes", "Shoulders"], "equipment": "Barbell" },
    { "name": "Landmine Deadlift", "bodyParts": ["Hamstrings", "Glutes"], "equipment": "Barbell" },
    { "name": "Landmine Row", "bodyParts": ["Back", "Lats"], "equipment": "Barbell" },
    { "name": "Landmine Press", "bodyParts": ["Shoulders", "Chest"], "equipment": "Barbell" },
    { "name": "Landmine Twist", "bodyParts": ["Obliques", "Core"], "equipment": "Barbell" },
    { "name": "Standing Cable Row", "bodyParts": ["Back", "Lats"], "equipment": "Cable" },
    { "name": "Standing Chest Fly", "bodyParts": ["Chest"], "equipment": "Cable" },
    { "name": "Incline Cable Fly", "bodyParts": ["Chest"], "equipment": "Cable" },
    { "name": "Decline Cable Fly", "bodyParts": ["Chest"], "equipment": "Cable" },
    { "name": "Seated Dumbbell Press", "bodyParts": ["Shoulders"], "equipment": "Dumbbell" },
    { "name": "Z Press", "bodyParts": ["Shoulders", "Core"], "equipment": "Barbell" },
    { "name": "Bradford Press", "bodyParts": ["Shoulders"], "equipment": "Barbell" },
    { "name": "Behind-the-Neck Press", "bodyParts": ["Shoulders"], "equipment": "Barbell" },
    { "name": "Lying Rear Delt Raise", "bodyParts": ["Rear Delts"], "equipment": "Dumbbell" },
    { "name": "Seated Rear Delt Fly", "bodyParts": ["Rear Delts"], "equipment": "Dumbbell" },
    { "name": "Incline Lateral Raise", "bodyParts": ["Shoulders"], "equipment": "Dumbbell" },
    { "name": "Cable Front Raise", "bodyParts": ["Front Delts"], "equipment": "Cable" },
    { "name": "Barbell Shrug", "bodyParts": ["Traps"], "equipment": "Barbell" },
    { "name": "Dumbbell Shrug", "bodyParts": ["Traps"], "equipment": "Dumbbell" },
    { "name": "Cable Shrug", "bodyParts": ["Traps"], "equipment": "Cable" },
    { "name": "Machine Shrug", "bodyParts": ["Traps"], "equipment": "Machine" },
    { "name": "Incline Push-Up", "bodyParts": ["Chest", "Triceps"], "equipment": "Bodyweight" },
    { "name": "Decline Push-Up", "bodyParts": ["Chest", "Shoulders"], "equipment": "Bodyweight" },
    { "name": "Clap Push-Up", "bodyParts": ["Chest", "Triceps"], "equipment": "Bodyweight" },
    { "name": "Diamond Push-Up", "bodyParts": ["Chest", "Triceps"], "equipment": "Bodyweight" },
    { "name": "Wide Push-Up", "bodyParts": ["Chest"], "equipment": "Bodyweight" },
    { "name": "Close-Grip Push-Up", "bodyParts": ["Triceps"], "equipment": "Bodyweight" },
    { "name": "Archer Push-Up", "bodyParts": ["Chest", "Triceps"], "equipment": "Bodyweight" },
    { "name": "Pike Push-Up", "bodyParts": ["Shoulders"], "equipment": "Bodyweight" },
    { "name": "Handstand Push-Up", "bodyParts": ["Shoulders", "Triceps"], "equipment": "Bodyweight" },
    { "name": "Ring Push-Up", "bodyParts": ["Chest", "Triceps"], "equipment": "Rings" },
    { "name": "Ring Dip", "bodyParts": ["Chest", "Triceps"], "equipment": "Rings" },
    { "name": "Assisted Pull-Up", "bodyParts": ["Back", "Biceps"], "equipment": "Machine" },
    { "name": "Neutral Grip Pull-Up", "bodyParts": ["Back", "Biceps"], "equipment": "Bodyweight" },
    { "name": "Weighted Pull-Up", "bodyParts": ["Back", "Biceps"], "equipment": "Belt" },
    { "name": "Wide-Grip Pull-Up", "bodyParts": ["Lats"], "equipment": "Bodyweight" },
    { "name": "Close-Grip Pull-Up", "bodyParts": ["Lats", "Biceps"], "equipment": "Bodyweight" },
    { "name": "Inverted Row", "bodyParts": ["Back", "Rear Delts"], "equipment": "Bar" },
    { "name": "Bodyweight Row", "bodyParts": ["Back"], "equipment": "Bodyweight" },
    { "name": "TRX Row", "bodyParts": ["Back", "Biceps"], "equipment": "TRX" },
    { "name": "TRX Chest Fly", "bodyParts": ["Chest"], "equipment": "TRX" },
    { "name": "TRX Biceps Curl", "bodyParts": ["Biceps"], "equipment": "TRX" },
    { "name": "TRX Triceps Extension", "bodyParts": ["Triceps"], "equipment": "TRX" },
    { "name": "TRX Y Fly", "bodyParts": ["Shoulders"], "equipment": "TRX" },
    { "name": "TRX T Fly", "bodyParts": ["Rear Delts"], "equipment": "TRX" },
    { "name": "TRX Reverse Fly", "bodyParts": ["Rear Delts"], "equipment": "TRX" },
    { "name": "Kettlebell Clean", "bodyParts": ["Hamstrings", "Back"], "equipment": "Kettlebell" },
    { "name": "Kettlebell Press", "bodyParts": ["Shoulders"], "equipment": "Kettlebell" },
    { "name": "Kettlebell Snatch", "bodyParts": ["Shoulders", "Back"], "equipment": "Kettlebell" },
    { "name": "Kettlebell Goblet Squat", "bodyParts": ["Quads", "Glutes"], "equipment": "Kettlebell" },
    { "name": "Kettlebell Front Squat", "bodyParts": ["Quads", "Glutes"], "equipment": "Kettlebell" },
    { "name": "Kettlebell Deadlift", "bodyParts": ["Hamstrings", "Glutes"], "equipment": "Kettlebell" },
    { "name": "Kettlebell Lunge", "bodyParts": ["Quads", "Glutes"], "equipment": "Kettlebell" },
    { "name": "Kettlebell Romanian Deadlift", "bodyParts": ["Hamstrings"], "equipment": "Kettlebell" },
    { "name": "Kettlebell Row", "bodyParts": ["Back", "Lats"], "equipment": "Kettlebell" },
    { "name": "Kettlebell Floor Press", "bodyParts": ["Chest", "Triceps"], "equipment": "Kettlebell" },
    { "name": "Kettlebell Push Press", "bodyParts": ["Shoulders"], "equipment": "Kettlebell" },
    { "name": "Kettlebell High Pull", "bodyParts": ["Traps", "Shoulders"], "equipment": "Kettlebell" },
    { "name": "Kettlebell Windmill", "bodyParts": ["Core", "Shoulders"], "equipment": "Kettlebell" },
    { "name": "Kettlebell Lateral Swing", "bodyParts": ["Obliques"], "equipment": "Kettlebell" },
    { "name": "Kettlebell Halo", "bodyParts": ["Shoulders", "Core"], "equipment": "Kettlebell" },
    { "name": "Clean and Press", "bodyParts": ["Full Body"], "equipment": "Barbell" },
    { "name": "Power Clean", "bodyParts": ["Full Body"], "equipment": "Barbell" },
    { "name": "Snatch", "bodyParts": ["Full Body"], "equipment": "Barbell" },
    { "name": "Hang Clean", "bodyParts": ["Full Body"], "equipment": "Barbell" },
    { "name": "Push Jerk", "bodyParts": ["Shoulders", "Legs"], "equipment": "Barbell" },
    { "name": "Split Jerk", "bodyParts": ["Shoulders", "Legs"], "equipment": "Barbell" },
    { "name": "Overhead Squat", "bodyParts": ["Quads", "Shoulders", "Core"], "equipment": "Barbell" },
    { "name": "Front Rack Lunge", "bodyParts": ["Quads", "Glutes"], "equipment": "Barbell" },
    { "name": "Zercher Squat", "bodyParts": ["Quads", "Glutes", "Core"], "equipment": "Barbell" },
    { "name": "Jefferson Deadlift", "bodyParts": ["Hamstrings", "Glutes"], "equipment": "Barbell" },
    { "name": "Sumo Squat", "bodyParts": ["Glutes", "Quads", "Adductors"], "equipment": "Dumbbell" },
    { "name": "Side Lunge", "bodyParts": ["Quads", "Glutes", "Adductors"], "equipment": "Bodyweight" },
    { "name": "Cossack Squat", "bodyParts": ["Quads", "Adductors"], "equipment": "Bodyweight" },
    { "name": "Single-Leg Press", "bodyParts": ["Quads", "Glutes"], "equipment": "Machine" },
    { "name": "Kneeling Squat", "bodyParts": ["Glutes"], "equipment": "Barbell" },
    { "name": "Curtsy Lunge", "bodyParts": ["Glutes", "Adductors"], "equipment": "Dumbbell" },
    { "name": "Split Squat Jump", "bodyParts": ["Quads", "Glutes"], "equipment": "Bodyweight" },
    { "name": "Jump Squat", "bodyParts": ["Quads", "Glutes"], "equipment": "Bodyweight" },
    { "name": "Broad Jump", "bodyParts": ["Quads", "Glutes"], "equipment": "Bodyweight" },
    { "name": "Box Jump", "bodyParts": ["Quads", "Glutes"], "equipment": "Bodyweight" },
    { "name": "Depth Jump", "bodyParts": ["Quads", "Glutes"], "equipment": "Bodyweight" },
    { "name": "Knee Tuck Jump", "bodyParts": ["Quads", "Glutes"], "equipment": "Bodyweight" },
    { "name": "Wall Sit", "bodyParts": ["Quads"], "equipment": "Bodyweight" },
    { "name": "Glute March", "bodyParts": ["Glutes"], "equipment": "Bodyweight" },
    { "name": "Glute Step Back", "bodyParts": ["Glutes"], "equipment": "Bodyweight" },
    { "name": "Donkey Kick", "bodyParts": ["Glutes"], "equipment": "Bodyweight" },
    { "name": "Fire Hydrant", "bodyParts": ["Glutes"], "equipment": "Bodyweight" },
    { "name": "Frog Pump", "bodyParts": ["Glutes"], "equipment": "Bodyweight" },
    { "name": "Nordic Hamstring Curl", "bodyParts": ["Hamstrings"], "equipment": "Partner/Bench" },
    { "name": "Reverse Hyperextension", "bodyParts": ["Glutes", "Hamstrings", "Lower Back"], "equipment": "Machine" },
    { "name": "Hip Airplane", "bodyParts": ["Glutes", "Core"], "equipment": "Bodyweight" },
    { "name": "Hip Circle Walk", "bodyParts": ["Glutes"], "equipment": "Band" },
    { "name": "Monster Walk", "bodyParts": ["Glutes"], "equipment": "Band" },
    { "name": "Banded Squat", "bodyParts": ["Quads", "Glutes"], "equipment": "Band" },
    { "name": "Banded Deadlift", "bodyParts": ["Hamstrings", "Glutes"], "equipment": "Band" },
    { "name": "Sissy Squat (Bodyweight)", "bodyParts": ["Quads"], "equipment": "Bodyweight" },
    { "name": "Smith Machine Squat", "bodyParts": ["Quads", "Glutes"], "equipment": "Smith Machine" },
    { "name": "Smith Machine Lunge", "bodyParts": ["Quads", "Glutes"], "equipment": "Smith Machine" },
    { "name": "Smith Machine RDL", "bodyParts": ["Hamstrings", "Glutes"], "equipment": "Smith Machine" },
    { "name": "Smith Machine Bench Press", "bodyParts": ["Chest", "Triceps"], "equipment": "Smith Machine" },
    { "name": "Smith Machine Shoulder Press", "bodyParts": ["Shoulders"], "equipment": "Smith Machine" },
    { "name": "Smith Machine Row", "bodyParts": ["Back"], "equipment": "Smith Machine" },
    { "name": "Smith Machine Calf Raise", "bodyParts": ["Calves"], "equipment": "Smith Machine" },
    { "name": "Pendlay Row", "bodyParts": ["Back", "Lats"], "equipment": "Barbell" },
    { "name": "Seal Row", "bodyParts": ["Back", "Lats"], "equipment": "Barbell" },
    { "name": "Chest-Supported Dumbbell Row", "bodyParts": ["Back", "Lats"], "equipment": "Dumbbell" },
    { "name": "Wide-Grip Barbell Row", "bodyParts": ["Back", "Rear Delts"], "equipment": "Barbell" },
    { "name": "Seal Row (Dumbbells)", "bodyParts": ["Back", "Lats"], "equipment": "Dumbbell" },
    { "name": "Machine High Row", "bodyParts": ["Lats", "Rear Delts"], "equipment": "Machine" },
    { "name": "Machine Low Row", "bodyParts": ["Lats", "Rhomboids"], "equipment": "Machine" },
    { "name": "Meadow Shrug", "bodyParts": ["Traps"], "equipment": "Barbell" },
    { "name": "Chest-Supported T-Bar Row", "bodyParts": ["Back"], "equipment": "Machine" },
    { "name": "Yates Row", "bodyParts": ["Back", "Lats"], "equipment": "Barbell" },
    { "name": "Seated Cable Wide Row", "bodyParts": ["Back", "Rear Delts"], "equipment": "Cable" },
    { "name": "V-Bar Pulldown", "bodyParts": ["Lats"], "equipment": "Machine" },
    { "name": "Single-Arm Lat Pulldown", "bodyParts": ["Lats"], "equipment": "Cable" },
    { "name": "Kneeling Lat Pulldown", "bodyParts": ["Lats"], "equipment": "Cable" },
    { "name": "Straight-Bar Pushdown", "bodyParts": ["Triceps"], "equipment": "Cable" },
    { "name": "Reverse-Grip Pushdown", "bodyParts": ["Triceps"], "equipment": "Cable" },
    { "name": "Single-Arm Cable Pushdown", "bodyParts": ["Triceps"], "equipment": "Cable" },
    { "name": "Cross-Body Triceps Extension", "bodyParts": ["Triceps"], "equipment": "Cable" },
    { "name": "JM Press", "bodyParts": ["Triceps", "Chest"], "equipment": "Barbell" },
    { "name": "Board Press", "bodyParts": ["Chest", "Triceps"], "equipment": "Barbell" },
    { "name": "Spoto Press", "bodyParts": ["Chest", "Triceps"], "equipment": "Barbell" },
    { "name": "Floor Press", "bodyParts": ["Chest", "Triceps"], "equipment": "Barbell" },
    { "name": "Pin Press", "bodyParts": ["Chest", "Triceps"], "equipment": "Barbell" },
    { "name": "Close-Grip Push-Up on Handles", "bodyParts": ["Triceps", "Chest"], "equipment": "Bodyweight" },
    { "name": "Cable Chest Press", "bodyParts": ["Chest"], "equipment": "Cable" },
    { "name": "Guillotine Press", "bodyParts": ["Chest"], "equipment": "Barbell" },
    { "name": "Incline Machine Press", "bodyParts": ["Chest", "Shoulders"], "equipment": "Machine" },
    { "name": "Decline Machine Press", "bodyParts": ["Chest"], "equipment": "Machine" },
    { "name": "Neutral-Grip Dumbbell Press", "bodyParts": ["Chest", "Triceps"], "equipment": "Dumbbell" },
    { "name": "Dumbbell Squeeze Press", "bodyParts": ["Chest", "Triceps"], "equipment": "Dumbbell" },
    { "name": "Low Cable Fly", "bodyParts": ["Chest"], "equipment": "Cable" },
    { "name": "High Cable Fly", "bodyParts": ["Chest"], "equipment": "Cable" },
    { "name": "Cable Iron Cross", "bodyParts": ["Chest"], "equipment": "Cable" },
    { "name": "Machine Pec Fly (Reverse Grip)", "bodyParts": ["Chest"], "equipment": "Machine" },
    { "name": "Floor Fly (Dumbbells)", "bodyParts": ["Chest"], "equipment": "Dumbbell" },
    { "name": "Incline Hammer Curl", "bodyParts": ["Biceps", "Forearms"], "equipment": "Dumbbell" },
    { "name": "Zottman Curl", "bodyParts": ["Biceps", "Forearms"], "equipment": "Dumbbell" },
    { "name": "Spider Curl", "bodyParts": ["Biceps"], "equipment": "EZ Bar" },
    { "name": "Cable Preacher Curl", "bodyParts": ["Biceps"], "equipment": "Cable" },
    { "name": "Drag Curl", "bodyParts": ["Biceps"], "equipment": "Barbell" },
    { "name": "Reverse-Grip EZ-Bar Curl", "bodyParts": ["Forearms", "Biceps"], "equipment": "EZ Bar" },
    { "name": "Seated Alternating Curl", "bodyParts": ["Biceps"], "equipment": "Dumbbell" },
    { "name": "Bayesian Cable Curl", "bodyParts": ["Biceps"], "equipment": "Cable" },
    { "name": "Overhead Cable Curl", "bodyParts": ["Biceps"], "equipment": "Cable" },
    { "name": "Incline Cable Curl", "bodyParts": ["Biceps"], "equipment": "Cable" },
    { "name": "Cross-Body Hammer Curl", "bodyParts": ["Biceps", "Forearms"], "equipment": "Dumbbell" },
    { "name": "Seated Calf Raise (Dumbbell on Knee)", "bodyParts": ["Calves"], "equipment": "Dumbbell" },
    { "name": "Single-Leg Calf Raise", "bodyParts": ["Calves"], "equipment": "Bodyweight" },
    { "name": "Leg Press Calf Raise", "bodyParts": ["Calves"], "equipment": "Machine" },
    { "name": "Smith Machine Calf Raise (Seated)", "bodyParts": ["Calves"], "equipment": "Smith Machine" },
    { "name": "Cable Upright Row", "bodyParts": ["Shoulders", "Traps"], "equipment": "Cable" },
    { "name": "Dumbbell Upright Row", "bodyParts": ["Shoulders", "Traps"], "equipment": "Dumbbell" },
    { "name": "Kettlebell Upright Row", "bodyParts": ["Shoulders", "Traps"], "equipment": "Kettlebell" },
    { "name": "Rear Delt Row", "bodyParts": ["Rear Delts"], "equipment": "Dumbbell" },
    { "name": "Prone Y Raise", "bodyParts": ["Shoulders", "Upper Back"], "equipment": "Bodyweight" },
    { "name": "Prone T Raise", "bodyParts": ["Rear Delts", "Upper Back"], "equipment": "Bodyweight" },
    { "name": "Cuban Press", "bodyParts": ["Shoulders", "Rotator Cuff"], "equipment": "Dumbbell" },
    { "name": "External Rotation (Cable)", "bodyParts": ["Rotator Cuff"], "equipment": "Cable" },
    { "name": "Internal Rotation (Cable)", "bodyParts": ["Rotator Cuff"], "equipment": "Cable" },
    { "name": "Face Pull (Rope High)", "bodyParts": ["Rear Delts", "Traps"], "equipment": "Cable" },
    { "name": "Face Pull (Rope Low)", "bodyParts": ["Rear Delts", "Traps"], "equipment": "Cable" },
    { "name": "Smith Machine Upright Row", "bodyParts": ["Shoulders", "Traps"], "equipment": "Smith Machine" },
    { "name": "Serratus Punch", "bodyParts": ["Serratus", "Shoulders"], "equipment": "Cable" },
    { "name": "Pullover (Dumbbell)", "bodyParts": ["Lats", "Chest"], "equipment": "Dumbbell" },
    { "name": "Pullover (Machine)", "bodyParts": ["Lats"], "equipment": "Machine" },
    { "name": "Pullover (Cable)", "bodyParts": ["Lats"], "equipment": "Cable" },
    { "name": "Seal Row Machine", "bodyParts": ["Back", "Lats"], "equipment": "Machine" },
    { "name": "Iso-Lateral Row", "bodyParts": ["Back", "Lats"], "equipment": "Machine" },
    { "name": "Iso-Lateral Chest Press", "bodyParts": ["Chest"], "equipment": "Machine" },
    { "name": "Iso-Lateral Shoulder Press", "bodyParts": ["Shoulders"], "equipment": "Machine" },
    { "name": "Single-Leg Romanian Deadlift (Bodyweight)", "bodyParts": ["Hamstrings", "Glutes"], "equipment": "Bodyweight" },
    { "name": "B-Stance RDL", "bodyParts": ["Hamstrings", "Glutes"], "equipment": "Dumbbell" },
    { "name": "Hip Hinge Drill", "bodyParts": ["Hamstrings", "Glutes"], "equipment": "Bodyweight" },
    { "name": "Band-Resisted Hip Thrust", "bodyParts": ["Glutes"], "equipment": "Band" },
    { "name": "Smith Machine Hip Thrust", "bodyParts": ["Glutes"], "equipment": "Smith Machine" },
    { "name": "Cable Hip Abduction (Standing)", "bodyParts": ["Glutes"], "equipment": "Cable" },
    { "name": "Cable Hip Adduction (Standing)", "bodyParts": ["Adductors"], "equipment": "Cable" },
    { "name": "Copenhagen Plank", "bodyParts": ["Adductors", "Core"], "equipment": "Bodyweight" },
    { "name": "Nordic Adductor", "bodyParts": ["Adductors"], "equipment": "Bodyweight" },
    { "name": "Sled March", "bodyParts": ["Quads", "Glutes", "Calves"], "equipment": "Sled" },
    { "name": "Sled Row", "bodyParts": ["Back", "Biceps"], "equipment": "Sled" },
    { "name": "Sled Chest Press", "bodyParts": ["Chest", "Triceps"], "equipment": "Sled" },
    { "name": "Ski Erg Pull", "bodyParts": ["Back", "Triceps", "Core"], "equipment": "Machine" },
    { "name": "Air Bike Sprint", "bodyParts": ["Full Body"], "equipment": "Machine" },
    { "name": "Rowing Ergometer", "bodyParts": ["Back", "Legs", "Cardio"], "equipment": "Machine" },
    { "name": "Treadmill Incline Walk", "bodyParts": ["Legs", "Cardio"], "equipment": "Machine" },
    { "name": "Stair Climber", "bodyParts": ["Quads", "Glutes", "Calves"], "equipment": "Machine" },
    { "name": "Battle Rope Waves", "bodyParts": ["Shoulders", "Arms", "Cardio"], "equipment": "Ropes" },
    { "name": "Nordic Curl (Assisted)", "bodyParts": ["Hamstrings"], "equipment": "Bodyweight" },
    { "name": "Cable Leg Extension", "bodyParts": ["Quads"], "equipment": "Cable" },
    { "name": "Cable Leg Curl", "bodyParts": ["Hamstrings"], "equipment": "Cable" },
    { "name": "Barbell Glute Bridge", "bodyParts": ["Glutes", "Hamstrings"], "equipment": "Barbell" },
    { "name": "Resistance Band Hip Thrust", "bodyParts": ["Glutes"], "equipment": "Band" },
    { "name": "Standing Leg Curl (Machine)", "bodyParts": ["Hamstrings"], "equipment": "Machine" },
    { "name": "Single-Leg Curl", "bodyParts": ["Hamstrings"], "equipment": "Machine" },
    { "name": "Seated Leg Press (Wide Stance)", "bodyParts": ["Glutes", "Hamstrings"], "equipment": "Machine" },
    { "name": "Seated Leg Press (Narrow Stance)", "bodyParts": ["Quads"], "equipment": "Machine" },
    { "name": "Reverse Lunge (Barbell)", "bodyParts": ["Glutes", "Quads"], "equipment": "Barbell" },
    { "name": "Front Foot Elevated Split Squat", "bodyParts": ["Quads", "Glutes"], "equipment": "Dumbbell" },
    { "name": "Heel Elevated Squat", "bodyParts": ["Quads"], "equipment": "Barbell" },
    { "name": "Toes Elevated RDL", "bodyParts": ["Hamstrings"], "equipment": "Dumbbell" },
    { "name": "Jefferson Squat", "bodyParts": ["Glutes", "Quads"], "equipment": "Barbell" },
    { "name": "Barbell Hip Thrust (Feet Elevated)", "bodyParts": ["Glutes"], "equipment": "Barbell" },
    { "name": "Barbell Good Morning (Seated)", "bodyParts": ["Hamstrings", "Lower Back"], "equipment": "Barbell" },
    { "name": "Seated Good Morning", "bodyParts": ["Hamstrings", "Lower Back"], "equipment": "Barbell" },
    { "name": "Back Extension", "bodyParts": ["Lower Back", "Glutes"], "equipment": "Machine" },
    { "name": "Reverse Hyper", "bodyParts": ["Glutes", "Hamstrings", "Lower Back"], "equipment": "Machine" },
    { "name": "Cable Glute Kickback (Kneeling)", "bodyParts": ["Glutes"], "equipment": "Cable" },
    { "name": "Smith Machine Romanian Deadlift", "bodyParts": ["Hamstrings", "Glutes"], "equipment": "Smith Machine" },
    { "name": "Smith Machine Split Squat", "bodyParts": ["Quads", "Glutes"], "equipment": "Smith Machine" },
    { "name": "Smith Machine Front Squat", "bodyParts": ["Quads", "Glutes"], "equipment": "Smith Machine" },
    { "name": "Smith Machine Deadlift", "bodyParts": ["Hamstrings", "Glutes"], "equipment": "Smith Machine" },
    { "name": "Smith Machine Calf Raise (Standing)", "bodyParts": ["Calves"], "equipment": "Smith Machine" },
    { "name": "Machine Hack Squat (Reverse)", "bodyParts": ["Glutes", "Hamstrings"], "equipment": "Machine" },
    { "name": "V-Squat Machine", "bodyParts": ["Quads", "Glutes"], "equipment": "Machine" },
    { "name": "Pendulum Squat", "bodyParts": ["Quads", "Glutes"], "equipment": "Machine" },
    { "name": "Sled Hack Squat", "bodyParts": ["Quads", "Glutes"], "equipment": "Machine" },
    { "name": "Leg Press (Single Leg)", "bodyParts": ["Quads", "Glutes"], "equipment": "Machine" },
    { "name": "45-Degree Leg Press", "bodyParts": ["Quads", "Glutes"], "equipment": "Machine" },
    { "name": "Hip Thrust (Smith Machine)", "bodyParts": ["Glutes"], "equipment": "Smith Machine" },
    { "name": "Hip Thrust (Machine)", "bodyParts": ["Glutes"], "equipment": "Machine" },
    { "name": "Barbell Walking Lunge", "bodyParts": ["Quads", "Glutes"], "equipment": "Barbell" },
    { "name": "Dumbbell Step-Up (High Box)", "bodyParts": ["Glutes", "Quads"], "equipment": "Dumbbell" },
    { "name": "Barbell Step-Up", "bodyParts": ["Glutes", "Quads"], "equipment": "Barbell" },
    { "name": "Smith Machine Step-Up", "bodyParts": ["Glutes", "Quads"], "equipment": "Smith Machine" },
    { "name": "Cable Step-Back Lunge", "bodyParts": ["Glutes", "Quads"], "equipment": "Cable" },
    { "name": "Barbell Lunge (Forward)", "bodyParts": ["Quads", "Glutes"], "equipment": "Barbell" },
    { "name": "Barbell Lunge (Reverse)", "bodyParts": ["Glutes", "Hamstrings"], "equipment": "Barbell" },
    { "name": "Cable Lateral Lunge", "bodyParts": ["Glutes", "Adductors"], "equipment": "Cable" },
    { "name": "Crossover Step Lunge", "bodyParts": ["Glutes", "Adductors"], "equipment": "Bodyweight" },
    { "name": "Glute Bridge (Single Leg)", "bodyParts": ["Glutes", "Hamstrings"], "equipment": "Bodyweight" },
    { "name": "Glute Bridge (Feet on Bench)", "bodyParts": ["Glutes"], "equipment": "Bodyweight" },
    { "name": "Cable Deadlift", "bodyParts": ["Hamstrings", "Glutes"], "equipment": "Cable" },
    { "name": "Resistance Band Deadlift", "bodyParts": ["Hamstrings", "Glutes"], "equipment": "Band" },
    { "name": "Resistance Band Squat", "bodyParts": ["Quads", "Glutes"], "equipment": "Band" },
    { "name": "Resistance Band Lateral Walk", "bodyParts": ["Glutes"], "equipment": "Band" },
    { "name": "Resistance Band Kickback", "bodyParts": ["Glutes"], "equipment": "Band" },
    { "name": "Resistance Band Hip Abduction", "bodyParts": ["Glutes"], "equipment": "Band" },
    { "name": "Resistance Band Hip Adduction", "bodyParts": ["Adductors"], "equipment": "Band" },
    { "name": "Resistance Band Good Morning", "bodyParts": ["Hamstrings", "Glutes"], "equipment": "Band" },
    { "name": "Resistance Band Leg Press", "bodyParts": ["Quads", "Glutes"], "equipment": "Band" },
    { "name": "Cable Front Squat", "bodyParts": ["Quads", "Core"], "equipment": "Cable" },
    { "name": "Cable Zercher Squat", "bodyParts": ["Quads", "Glutes", "Core"], "equipment": "Cable" },
    { "name": "Cable Deadlift to Row", "bodyParts": ["Back", "Hamstrings"], "equipment": "Cable" },
    { "name": "Cable Romanian Deadlift", "bodyParts": ["Hamstrings", "Glutes"], "equipment": "Cable" },
    { "name": "Cable Pull-In", "bodyParts": ["Glutes"], "equipment": "Cable" },
    { "name": "Cable Squat Row", "bodyParts": ["Back", "Glutes"], "equipment": "Cable" },
    { "name": "Cable Split Squat", "bodyParts": ["Quads", "Glutes"], "equipment": "Cable" },
    { "name": "Cable Hip Thrust", "bodyParts": ["Glutes"], "equipment": "Cable" },
    { "name": "Smith Machine Front Lunge", "bodyParts": ["Quads", "Glutes"], "equipment": "Smith Machine" },
    { "name": "Smith Machine Reverse Lunge", "bodyParts": ["Glutes", "Hamstrings"], "equipment": "Smith Machine" },
    { "name": "Smith Machine Good Morning", "bodyParts": ["Hamstrings", "Glutes"], "equipment": "Smith Machine" },
    { "name": "Smith Machine Sumo Deadlift", "bodyParts": ["Glutes", "Hamstrings"], "equipment": "Smith Machine" },
    { "name": "Smith Machine Sumo Squat", "bodyParts": ["Glutes", "Quads", "Adductors"], "equipment": "Smith Machine" },
    { "name": "Smith Machine Hack Squat", "bodyParts": ["Quads"], "equipment": "Smith Machine" },
    { "name": "Seated Smith Machine Shoulder Press", "bodyParts": ["Shoulders"], "equipment": "Smith Machine" },
    { "name": "Smith Machine Incline Press", "bodyParts": ["Chest", "Shoulders"], "equipment": "Smith Machine" },
    { "name": "Smith Machine Decline Press", "bodyParts": ["Chest"], "equipment": "Smith Machine" },
    { "name": "Smith Machine Bench Press", "bodyParts": ["Chest"], "equipment": "Smith Machine" },
    { "name": "Smith Machine Shrug", "bodyParts": ["Traps"], "equipment": "Smith Machine" },
    { "name": "Cable Chest Press (Standing)", "bodyParts": ["Chest"], "equipment": "Cable" },
    { "name": "Cable Incline Press", "bodyParts": ["Chest", "Shoulders"], "equipment": "Cable" },
    { "name": "Cable Decline Press", "bodyParts": ["Chest"], "equipment": "Cable" },
    { "name": "Cable Reverse Fly", "bodyParts": ["Rear Delts"], "equipment": "Cable" },
    { "name": "Cable Lateral Raise (Behind Back)", "bodyParts": ["Shoulders"], "equipment": "Cable" },
    { "name": "Cable Front Raise (Cross Body)", "bodyParts": ["Front Delts"], "equipment": "Cable" },
    { "name": "Cable Overhead Press", "bodyParts": ["Shoulders"], "equipment": "Cable" },
    { "name": "Cable Shoulder External Rotation", "bodyParts": ["Rotator Cuff"], "equipment": "Cable" },
    { "name": "Cable Shoulder Internal Rotation", "bodyParts": ["Rotator Cuff"], "equipment": "Cable" },
    { "name": "Cable Face Pull (Low Pulley)", "bodyParts": ["Rear Delts", "Traps"], "equipment": "Cable" },
    { "name": "Cable Rear Delt Row", "bodyParts": ["Rear Delts"], "equipment": "Cable" },
    { "name": "Cable High Row", "bodyParts": ["Lats", "Rear Delts"], "equipment": "Cable" },
    { "name": "Cable Pullover", "bodyParts": ["Lats"], "equipment": "Cable" },
    { "name": "Cable Bent-Over Row", "bodyParts": ["Back"], "equipment": "Cable" },
    { "name": "Cable Standing Row", "bodyParts": ["Back"], "equipment": "Cable" },
    { "name": "Cable Upright Row (Rope)", "bodyParts": ["Shoulders", "Traps"], "equipment": "Cable" },
    { "name": "Cable Curl (Rope)", "bodyParts": ["Biceps"], "equipment": "Cable" },
    { "name": "Cable Reverse Curl (Rope)", "bodyParts": ["Forearms"], "equipment": "Cable" },
    { "name": "Cable Hammer Curl", "bodyParts": ["Biceps", "Forearms"], "equipment": "Cable" },
    { "name": "Cable Concentration Curl", "bodyParts": ["Biceps"], "equipment": "Cable" },
    { "name": "Cable Incline Curl", "bodyParts": ["Biceps"], "equipment": "Cable" },
    { "name": "Cable Spider Curl", "bodyParts": ["Biceps"], "equipment": "Cable" },
    { "name": "Cable Reverse Grip Pulldown", "bodyParts": ["Lats", "Biceps"], "equipment": "Cable" },
    { "name": "Cable V-Bar Row", "bodyParts": ["Lats"], "equipment": "Cable" },
    { "name": "Cable Single-Arm Row", "bodyParts": ["Back"], "equipment": "Cable" },
    { "name": "Cable Neutral Grip Pulldown", "bodyParts": ["Lats"], "equipment": "Cable" },
    { "name": "Cable Lat Pushdown", "bodyParts": ["Lats"], "equipment": "Cable" },
    { "name": "Cable Rope Extension", "bodyParts": ["Triceps"], "equipment": "Cable" },
    { "name": "Cable Overhead Rope Extension", "bodyParts": ["Triceps"], "equipment": "Cable" },
    { "name": "Cable Kickback (Triceps)", "bodyParts": ["Triceps"], "equipment": "Cable" },
    { "name": "Cable Close Grip Press", "bodyParts": ["Triceps", "Chest"], "equipment": "Cable" },
    { "name": "Cable Chest Fly (High Pulley)", "bodyParts": ["Chest"], "equipment": "Cable" },
    { "name": "Cable Chest Fly (Low Pulley)", "bodyParts": ["Chest"], "equipment": "Cable" },
    { "name": "Cable Front Double Raise", "bodyParts": ["Shoulders"], "equipment": "Cable" },
    { "name": "Cable Crossover (Mid Pulley)", "bodyParts": ["Chest"], "equipment": "Cable" },
    { "name": "Cable Reverse Curl", "bodyParts": ["Forearms"], "equipment": "Cable" },
    { "name": "Cable Wrist Curl", "bodyParts": ["Forearms"], "equipment": "Cable" },
    { "name": "Cable Wrist Extension", "bodyParts": ["Forearms"], "equipment": "Cable" },
    { "name": "Cable Crunch (Kneeling)", "bodyParts": ["Abs"], "equipment": "Cable" },
    { "name": "Cable Side Crunch", "bodyParts": ["Obliques"], "equipment": "Cable" },
    { "name": "Cable Russian Twist", "bodyParts": ["Obliques"], "equipment": "Cable" },
    { "name": "Cable Woodchopper (High to Low)", "bodyParts": ["Obliques"], "equipment": "Cable" },
    { "name": "Cable Woodchopper (Low to High)", "bodyParts": ["Obliques"], "equipment": "Cable" },
    { "name": "Cable Standing Oblique Crunch", "bodyParts": ["Obliques"], "equipment": "Cable" },
    { "name": "Cable Plank Row", "bodyParts": ["Back", "Core"], "equipment": "Cable" },
    { "name": "Cable Pallof Press", "bodyParts": ["Core"], "equipment": "Cable" },
    { "name": "Cable Twist Press", "bodyParts": ["Obliques", "Core"], "equipment": "Cable" },
    { "name": "Cable Standing Twist", "bodyParts": ["Obliques"], "equipment": "Cable" },
    { "name": "Cable Incline Curl", "bodyParts": ["Biceps"], "equipment": "Cable" },
    { "name": "Cable Reverse Curl", "bodyParts": ["Forearms", "Biceps"], "equipment": "Cable" },
    { "name": "Cable Wrist Flexion", "bodyParts": ["Forearms"], "equipment": "Cable" },
    { "name": "Cable Wrist Extension", "bodyParts": ["Forearms"], "equipment": "Cable" },
    { "name": "Cable Lying Curl", "bodyParts": ["Biceps"], "equipment": "Cable" },
    { "name": "Cable Standing Twist", "bodyParts": ["Obliques"], "equipment": "Cable" },
    { "name": "Cable Pallof Hold", "bodyParts": ["Core"], "equipment": "Cable" },
    { "name": "Cable Side Bend", "bodyParts": ["Obliques"], "equipment": "Cable" },
    { "name": "Cable Rope Crunch", "bodyParts": ["Abs"], "equipment": "Cable" },
    { "name": "Cable Jackknife", "bodyParts": ["Abs"], "equipment": "Cable" },
    { "name": "Cable Reverse Crunch", "bodyParts": ["Abs"], "equipment": "Cable" },
    { "name": "Cable Lunge", "bodyParts": ["Quads", "Glutes"], "equipment": "Cable" },
    { "name": "Cable Sumo Deadlift", "bodyParts": ["Glutes", "Hamstrings"], "equipment": "Cable" },
    { "name": "Cable Step-Up", "bodyParts": ["Quads", "Glutes"], "equipment": "Cable" },
    { "name": "Cable Split Squat", "bodyParts": ["Quads", "Glutes"], "equipment": "Cable" },
    { "name": "Cable Lateral Lunge", "bodyParts": ["Adductors", "Glutes"], "equipment": "Cable" },
    { "name": "Cable Sumo Squat", "bodyParts": ["Quads", "Glutes", "Adductors"], "equipment": "Cable" },
    { "name": "Cable Romanian Deadlift", "bodyParts": ["Hamstrings", "Glutes"], "equipment": "Cable" },
    { "name": "Cable Glute Bridge", "bodyParts": ["Glutes"], "equipment": "Cable" },
    { "name": "Cable Hip Drive", "bodyParts": ["Glutes"], "equipment": "Cable" },
    { "name": "Cable Hamstring Curl", "bodyParts": ["Hamstrings"], "equipment": "Cable" },
    { "name": "Cable Leg Extension", "bodyParts": ["Quads"], "equipment": "Cable" },
    { "name": "Cable Calf Raise", "bodyParts": ["Calves"], "equipment": "Cable" },
    { "name": "Cable Heel Raise", "bodyParts": ["Calves"], "equipment": "Cable" },
    { "name": "Cable Adduction", "bodyParts": ["Adductors"], "equipment": "Cable" },
    { "name": "Cable Abduction", "bodyParts": ["Glutes"], "equipment": "Cable" },
    { "name": "Cable Leg Press", "bodyParts": ["Quads", "Glutes"], "equipment": "Cable" },
    { "name": "Cable Donkey Kick", "bodyParts": ["Glutes"], "equipment": "Cable" },
    { "name": "Cable Frog Kick", "bodyParts": ["Glutes"], "equipment": "Cable" },
    { "name": "Cable Step-Back Lunge", "bodyParts": ["Glutes", "Hamstrings"], "equipment": "Cable" },
    { "name": "Cable Front Raise", "bodyParts": ["Shoulders"], "equipment": "Cable" },
    { "name": "Cable Rear Delt Fly", "bodyParts": ["Rear Delts"], "equipment": "Cable" },
    { "name": "Cable Y Raise", "bodyParts": ["Shoulders"], "equipment": "Cable" },
    { "name": "Cable T Raise", "bodyParts": ["Rear Delts"], "equipment": "Cable" },
    { "name": "Cable Face Pull", "bodyParts": ["Rear Delts", "Traps"], "equipment": "Cable" },
    { "name": "Cable Upright Row", "bodyParts": ["Traps", "Shoulders"], "equipment": "Cable" },
    { "name": "Cable High Row", "bodyParts": ["Back", "Rear Delts"], "equipment": "Cable" },
    { "name": "Cable Low Row", "bodyParts": ["Back"], "equipment": "Cable" },
    { "name": "Cable Chest Press", "bodyParts": ["Chest"], "equipment": "Cable" },
    { "name": "Cable Crossover", "bodyParts": ["Chest"], "equipment": "Cable" },
    { "name": "Cable Incline Crossover", "bodyParts": ["Chest"], "equipment": "Cable" },
    { "name": "Cable Decline Crossover", "bodyParts": ["Chest"], "equipment": "Cable" },
    { "name": "Cable Fly", "bodyParts": ["Chest"], "equipment": "Cable" },
    { "name": "Cable Pec Fly", "bodyParts": ["Chest"], "equipment": "Cable" },
    { "name": "Cable Floor Press", "bodyParts": ["Chest", "Triceps"], "equipment": "Cable" },
    { "name": "Cable Shoulder Press", "bodyParts": ["Shoulders"], "equipment": "Cable" },
    { "name": "Cable Arnold Press", "bodyParts": ["Shoulders"], "equipment": "Cable" },
    { "name": "Cable Overhead Triceps Extension", "bodyParts": ["Triceps"], "equipment": "Cable" },
    { "name": "Cable Pushdown", "bodyParts": ["Triceps"], "equipment": "Cable" },
    { "name": "Cable Kickback", "bodyParts": ["Triceps"], "equipment": "Cable" },
    { "name": "Cable Overhead Curl", "bodyParts": ["Biceps"], "equipment": "Cable" },
    { "name": "Cable Drag Curl", "bodyParts": ["Biceps"], "equipment": "Cable" },
    { "name": "Cable Preacher Curl", "bodyParts": ["Biceps"], "equipment": "Cable" },
    { "name": "Cable Spider Curl", "bodyParts": ["Biceps"], "equipment": "Cable" },
    { "name": "Cable Reverse Grip Row", "bodyParts": ["Back"], "equipment": "Cable" },
    { "name": "Cable Neutral Grip Pulldown", "bodyParts": ["Back"], "equipment": "Cable" },
    { "name": "Cable Wide Grip Pulldown", "bodyParts": ["Back"], "equipment": "Cable" },
    { "name": "Cable Straight Arm Pulldown", "bodyParts": ["Lats"], "equipment": "Cable" },
    { "name": "Cable Close Grip Pulldown", "bodyParts": ["Back"], "equipment": "Cable" },
    { "name": "Cable Incline Press", "bodyParts": ["Chest"], "equipment": "Cable" },
    { "name": "Cable Decline Press", "bodyParts": ["Chest"], "equipment": "Cable" },
    { "name": "Cable Squeeze Press", "bodyParts": ["Chest"], "equipment": "Cable" },
    { "name": "Cable Glute Kickback", "bodyParts": ["Glutes"], "equipment": "Cable" },
    { "name": "Cable Side Kick", "bodyParts": ["Glutes"], "equipment": "Cable" },
    { "name": "Cable Hip Abduction", "bodyParts": ["Glutes"], "equipment": "Cable" },
    { "name": "Cable Hip Adduction", "bodyParts": ["Adductors"], "equipment": "Cable" },
    { "name": "Cable Standing Crunch", "bodyParts": ["Abs"], "equipment": "Cable" },
    { "name": "Cable Side Crunch", "bodyParts": ["Obliques"], "equipment": "Cable" },
    { "name": "Cable Twist", "bodyParts": ["Obliques"], "equipment": "Cable" },
    { "name": "Cable Dead Bug", "bodyParts": ["Core"], "equipment": "Cable" },
    { "name": "Cable Bird Dog", "bodyParts": ["Core", "Glutes"], "equipment": "Cable" },
    { "name": "Cable Plank Pull", "bodyParts": ["Core"], "equipment": "Cable" },
    { "name": "Cable Standing Row", "bodyParts": ["Back"], "equipment": "Cable" },
    { "name": "Cable Bent Over Row", "bodyParts": ["Back"], "equipment": "Cable" },
    { "name": "Cable Sumo Row", "bodyParts": ["Back"], "equipment": "Cable" },
    { "name": "Cable Kneeling Row", "bodyParts": ["Back"], "equipment": "Cable" },
    { "name": "Cable V Bar Row", "bodyParts": ["Back"], "equipment": "Cable" },
    { "name": "Cable Low Pulley Row", "bodyParts": ["Back"], "equipment": "Cable" },
    { "name": "Cable Straight Bar Row", "bodyParts": ["Back"], "equipment": "Cable" },
    { "name": "Cable Rope Row", "bodyParts": ["Back"], "equipment": "Cable" },
    { "name": "Cable Lat Row", "bodyParts": ["Back"], "equipment": "Cable" },
    { "name": "Cable Iso Row", "bodyParts": ["Back"], "equipment": "Cable" },
    { "name": "Cable Lateral Step", "bodyParts": ["Glutes", "Adductors"], "equipment": "Cable" },
    { "name": "Cable Side Lunge", "bodyParts": ["Adductors", "Glutes"], "equipment": "Cable" },
    { "name": "Cable Frog Squat", "bodyParts": ["Glutes", "Adductors"], "equipment": "Cable" },
    { "name": "Cable Step Over", "bodyParts": ["Glutes", "Quads"], "equipment": "Cable" },
    { "name": "Cable Jump Squat", "bodyParts": ["Glutes", "Quads"], "equipment": "Cable" },
    { "name": "Cable Punch", "bodyParts": ["Chest", "Shoulders", "Core"], "equipment": "Cable" },
    { "name": "Cable Uppercut", "bodyParts": ["Chest", "Shoulders"], "equipment": "Cable" },
    { "name": "Cable Rotation", "bodyParts": ["Obliques", "Core"], "equipment": "Cable" },
    { "name": "Cable Diagonal Chop", "bodyParts": ["Obliques", "Core"], "equipment": "Cable" },
    { "name": "Cable Half Kneeling Press", "bodyParts": ["Chest", "Core"], "equipment": "Cable" },
    { "name": "Cable Half Kneeling Row", "bodyParts": ["Back", "Core"], "equipment": "Cable" },
    { "name": "Cable Lunge and Row", "bodyParts": ["Back", "Glutes"], "equipment": "Cable" },
    { "name": "Cable Crossover Lunge", "bodyParts": ["Glutes", "Adductors"], "equipment": "Cable" },
    { "name": "Cable Squat to Press", "bodyParts": ["Quads", "Glutes", "Shoulders"], "equipment": "Cable" },
    { "name": "Cable Lateral Raise Hold", "bodyParts": ["Shoulders"], "equipment": "Cable" },
    { "name": "Cable Pull Apart", "bodyParts": ["Rear Delts"], "equipment": "Cable" },
    { "name": "Cable Reverse Fly Hold", "bodyParts": ["Rear Delts"], "equipment": "Cable" },
    { "name": "Cable Shrug Hold", "bodyParts": ["Traps"], "equipment": "Cable" },
    { "name": "Cable Scaption", "bodyParts": ["Shoulders"], "equipment": "Cable" },
    { "name": "Cable Cuban Rotation", "bodyParts": ["Rotator Cuff"], "equipment": "Cable" },
    { "name": "Cable Scapular Retraction", "bodyParts": ["Upper Back"], "equipment": "Cable" },
    { "name": "Cable Rear Delt Row", "bodyParts": ["Rear Delts"], "equipment": "Cable" },
    { "name": "Cable Y Press", "bodyParts": ["Shoulders"], "equipment": "Cable" },
    { "name": "Cable Incline Y Raise", "bodyParts": ["Shoulders"], "equipment": "Cable" },
    { "name": "Cable Incline Front Raise", "bodyParts": ["Front Delts"], "equipment": "Cable" },
    { "name": "Cable Standing Reverse Curl", "bodyParts": ["Forearms"], "equipment": "Cable" },
    { "name": "Cable Wrist Curl Reverse", "bodyParts": ["Forearms"], "equipment": "Cable" },
    { "name": "Cable Standing Hip Flexion", "bodyParts": ["Hip Flexors"], "equipment": "Cable" },
    { "name": "Cable Donkey Calf Raise", "bodyParts": ["Calves"], "equipment": "Cable" },
    { "name": "Cable Lateral Step-Out", "bodyParts": ["Glutes"], "equipment": "Cable" },
    { "name": "Cable Side Plank Row", "bodyParts": ["Core", "Back"], "equipment": "Cable" },
    { "name": "Cable Single-Leg Deadlift", "bodyParts": ["Glutes", "Hamstrings"], "equipment": "Cable" },
    { "name": "Cable Power Clean", "bodyParts": ["Full Body"], "equipment": "Cable" },
    { "name": "Cable Thruster", "bodyParts": ["Legs", "Shoulders"], "equipment": "Cable" },
    { "name": "Cable Reverse Lunge with Curl", "bodyParts": ["Quads", "Biceps"], "equipment": "Cable" },
    { "name": "Cable Step-Up with Press", "bodyParts": ["Quads", "Shoulders"], "equipment": "Cable" },
    { "name": "Cable Curtsy Lunge", "bodyParts": ["Glutes", "Adductors"], "equipment": "Cable" },
    { "name": "Cable Overhead Squat", "bodyParts": ["Quads", "Core"], "equipment": "Cable" },
    { "name": "Cable Bear Crawl", "bodyParts": ["Full Body"], "equipment": "Cable" },
    { "name": "Cable Sled Push", "bodyParts": ["Quads", "Glutes"], "equipment": "Cable" },
    { "name": "Cable Sprint", "bodyParts": ["Full Body"], "equipment": "Cable" },
    { "name": "Cable Chest Pull", "bodyParts": ["Chest", "Shoulders"], "equipment": "Cable" },
    { "name": "Cable Lateral Fly", "bodyParts": ["Shoulders"], "equipment": "Cable" },
    { "name": "Cable Overhead Carry", "bodyParts": ["Core", "Shoulders"], "equipment": "Cable" },
    { "name": "Cable Suitcase Carry", "bodyParts": ["Core"], "equipment": "Cable" },
    { "name": "Cable Farmer’s Carry", "bodyParts": ["Forearms", "Core"], "equipment": "Cable" },
    { "name": "Cable Side Step Squat", "bodyParts": ["Glutes", "Quads"], "equipment": "Cable" },
    { "name": "Cable Jumping Jack", "bodyParts": ["Shoulders", "Legs"], "equipment": "Cable" },
    { "name": "Cable Crossover Crunch", "bodyParts": ["Abs"], "equipment": "Cable" },
    { "name": "Cable Cross Punch", "bodyParts": ["Chest", "Core"], "equipment": "Cable" },
    { "name": "Cable Dead Row", "bodyParts": ["Back", "Hamstrings"], "equipment": "Cable" },
    { "name": "Cable Lunge with Twist", "bodyParts": ["Core", "Legs"], "equipment": "Cable" },
    { "name": "Cable Standing Chop", "bodyParts": ["Core", "Obliques"], "equipment": "Cable" },
    { "name": "Cable Standing Lift", "bodyParts": ["Core", "Obliques"], "equipment": "Cable" }
    ]